Metadata-Version: 2.1
Name: policyengine-ng
Version: 0.5.1
Summary: Core microsimulation engine enabling country-specific policy models.
Home-page: https://github.com/policyengine/policyengine-core
Author: PolicyEngine
Author-email: hello@policyengine.org
License: https://www.fsf.org/licensing/licenses/agpl-3.0.html
Keywords: tax benefit microsimulation framework
Platform: UNKNOWN
Classifier: Development Status :: 5 - Production/Stable
Classifier: License :: OSI Approved :: GNU Affero General Public License v3
Classifier: Operating System :: POSIX
Classifier: Programming Language :: Python
Classifier: Programming Language :: Python :: 3.7
Classifier: Programming Language :: Python :: 3.8
Classifier: Programming Language :: Python :: 3.9
Classifier: Topic :: Scientific/Engineering :: Information Analysis
License-File: LICENSE
Requires-Dist: policyengine-core
Requires-Dist: numpy
Provides-Extra: dev
Requires-Dist: black ; extra == 'dev'
Requires-Dist: coverage ; extra == 'dev'
Requires-Dist: jupyter-book ; extra == 'dev'
Requires-Dist: plotly ; extra == 'dev'
Requires-Dist: pytest ; extra == 'dev'
Requires-Dist: setuptools ; extra == 'dev'
Requires-Dist: wheel ; extra == 'dev'
Requires-Dist: yaml-changelog (>=0.1.7) ; extra == 'dev'
Requires-Dist: linecheck ; extra == 'dev'
Requires-Dist: furo (<2023) ; extra == 'dev'
Requires-Dist: markupsafe (==2.0.1) ; extra == 'dev'
Requires-Dist: sphinx (<5,>=4.5.0) ; extra == 'dev'
Requires-Dist: sphinx-argparse (<1,>=0.3.2) ; extra == 'dev'
Requires-Dist: sphinx-math-dollar (<2,>=1.2.1) ; extra == 'dev'
